magic_codec.pth
magic_codec/__init__.py
magic_codec/codec.py
magic_codec/py.typed
magic_codec/register.py
magic_codec/builtin/__init__.py
magic_codec/builtin/braces.py
magic_codec/builtin/cpp.py
magic_codec/builtin/incdec.py
magic_codec/builtin/toml.py
magic_codec-0.0.1.dist-info/LICENSE
magic_codec-0.0.1.dist-info/METADATA
magic_codec-0.0.1.dist-info/WHEEL
magic_codec-0.0.1.dist-info/top_level.txt
magic_codec-0.0.1.dist-info/RECORD
